macro_photo/__init__.py
macro_photo/image_generator.py
mistral_image_gen/__init__.py
mistral_image_gen/image_generator.py
macro_photo-0.1.5.dist-info/LICENSE
macro_photo-0.1.5.dist-info/METADATA
macro_photo-0.1.5.dist-info/WHEEL
macro_photo-0.1.5.dist-info/top_level.txt
macro_photo-0.1.5.dist-info/RECORD
