Metadata-Version: 2.1
Name: macro-photo
Version: 0.1.5
Summary: A Python library for generating images using advanced AI technology
Home-page: https://github.com/macro-photo/macro-photo
Author: MacroPhoto
Author-email: bidifeb142@owube.com
Classifier: Programming Language :: Python :: 3
Classifier: License :: OSI Approved :: MIT License
Classifier: Operating System :: OS Independent
Requires-Python: >=3.6
License-File: LICENSE
Requires-Dist: requests>=2.31.0
Requires-Dist: colorama>=0.4.6
